Workbook

Sheet Исходные
A1: Исходные данные
A2: Астана · ЖК «Санды-кала 2» · собственное проживание одного человека
A3: СИНИЕ ЯЧЕЙКИ — можно менять · тёмные числа — формулы · размеры и стоимости требуют проверки
A4: Параметр | B4: Значение | C4: Единица / статус | D4: Источник / пояснение
A5: Город | B5: Астана | C5: подтверждено | D5: Сообщение пользователя
A6: Жилой комплекс | B6: Санды-кала 2 | C6: подтверждено | D6: Написание по сообщению пользователя
A7: Назначение | B7: Для себя | C7: подтверждено | D7: Денежная доходность не является главным критерием
A8: Число жильцов | B8: 1 | C8: человек | D8: Сообщение пользователя
A9: Общий бюджет | B9: 7000000 | C9: ₸ | D9: Лимит; не рыночная оценка стоимости ремонта
A10: Исключение из бюджета | B10: Крупная техника | C10: подтверждено | D10: Кухонная мебель, основная мебель, свет и текстиль включены в план распределения
A11: Условный горизонт сравнения | B11: 5 | C11: лет | D11: Редактируемое допущение для оценки стоимости личного удобства
A12: Учётная площадь квартиры | B12: 40.7 | C12: м² | D12: По техплану; пользователь указал около 41 м²
A13: Комната по экспликации | B13: 20.5 | C13: м² | D13: Существующая планировка
A14: Кухня по экспликации | B14: 8.9 | C14: м² | D14: Существующая планировка
A15: Коридор по экспликации | B15: 4.3 | C15: м² | D15: Существующая планировка
A16: Санузел по экспликации | B16: 5.1 | C16: м² | D16: Существующая планировка
A17: Лоджия: учётная добавка | B17: 1.9 | C17: м² | D17: Не равна полной геометрической площади лоджии
A18: Лоджия: длина | B18: 3.14 | C18: м | D18: Геометрическая реконструкция по схеме; проверить обмером
A19: Лоджия: ширина | B19: 1.21 | C19: м | D19: Геометрическая реконструкция по схеме; проверить обмером
A20: Комната: длина основного прямоугольника | B20: 6.94 | C20: м | D20: Предварительная геометрия; отделка и толщина стен не подтверждены
A21: Комната: ширина основного прямоугольника | B21: 3.1 | C21: м | D21: Предварительная геометрия
A22: Комната: длина вычитаемого участка | B22: 2.51 | C22: м | D22: Вычет из прямоугольника
... A38: Минимальная доля резерва | B38: 0.1 | C38: доля бюджета | D38: Рекомендуемый минимум 10%; резерв не расходуется заранее на улучшения
A40: Зафиксировано: 7 млн ₸ без крупной техники. Все размеры до обмера предварительные. Любое изменение источников пересчитывает формулы; остаток бюджета проверяется на листе «Бюджет».

Sheet Площади
A1: Проверка площадей
A2: Экспликация и геометрическая реконструкция показаны отдельно. Лоджия не присоединяется к жилой площади.
A3: СИНИЕ ЯЧЕЙКИ — можно менять · тёмные числа — формулы · размеры и стоимости требуют проверки
A4: Показатель | B4: Площадь / результат | C4: Единица | D4: Метод и ограничение
A5: Комната | B5: ='Исходные'!B13 -> 20.5 | C5: м² | D5: По экспликации
A6: Кухня | B6: ='Исходные'!B14 -> 8.9 | C6: м² | D6: По экспликации
A7: Коридор | B7: ='Исходные'!B15 -> 4.3 | C7: м² | D7: По экспликации
A8: Санузел | B8: ='Исходные'!B16 -> 5.1 | C8: м² | D8: По экспликации
A9: Полезная площадь | B9: =SUM(B5:B8) -> 38.8 | C9: м² | D9: Сумма четырёх помещений
A10: Учётная добавка лоджии | B10: ='Исходные'!B17 -> 1.9 | C10: м² | D10: Не полная геометрическая площадь лоджии
A11: Площадь с учётной добавкой | B11: =B9+B10 -> 40.7 | C11: м² | D11: 38,8 + 1,9
A12: Контрольная площадь техплана | B12: ='Исходные'!B12 -> 40.7 | C12: м² | D12: Для сверки
A13: Расхождение учётной площади | B13: =B11-B12 -> 0 | C13: м² | D13: Должно быть 0 при текущих исходных данных
A15: Геометрия по размерам
A16: Комната — по размерам | B16: ='Исходные'!B20*'Исходные'!B21-'Исходные'!B22*'Исходные'!B23 -> 20.4849 | C16: м² | D16: 6,94 × 3,10 − 2,51 × 0,41; округляется до 20,5 м²
A17: Кухня — по размерам | B17: ='Исходные'!B24*'Исходные'!B25-'Исходные'!B26*'Исходные'!B27 -> 8.8802 | C17: м² | D17: 3,14 × 3,31 − 0,78 × 1,94; округляется до 8,9 м²
A18: Лоджия — геометрическая площадь | B18: ='Исходные'!B18*'Исходные'!B19 -> 3.7994 | C18: м² | D18: 3,14 × 1,21; не добавлять к отапливаемой площади
A19: Отношение учётной добавки к геометрии | B19: =B10/B18 -> 0.50007896 | C19: доля | D19: Около 0,5; арифметическое отношение, не подтверждение нормативного коэффициента
A21: Условное деление комнаты на спальню и гостиную
A22: Спальня B/C — условная | B22: ='Исходные'!B28*'Исходные'!B21 -> 9.3 | C22: м² | D22: 3,00 × 3,10; предварительно, без проверки конструкции и отделки
A23: След новой перегородки | B23: ='Исходные'!B29*'Исходные'!B21 -> 0.31 | C23: м² | D23: 0,10 × 3,10; условная модель непрерывной стены
A24: Оставшаяся гостиная | B24: =B16-B22-B23 -> 10.8749 | C24: м² | D24: Площадь комнаты минус спальня и след перегородки
A25: Общая зона: кухня + гостиная | B25: =B24+B17 -> 19.7551 | C25: м² | D25: Арифметическая сумма; допустимость объединения ещё не подтверждена
A26: Контроль спальня + стена + общая зона | B26: =B22+B23+B25 -> 29.3651 | C26: м² | D26: Совпадает с комнатой и кухней по размерам
A27: Баланс реконструкции | B27: =B26-(B16+B17) -> 0 | C27: м² | D27: Должен быть 0; это проверка модели, не проверка возможности строительства
A29: Точность четырёх знаков показывает арифметику, а не точность обмера. Линии стен, проёмы, конструкция перегородок и слои отделки предварительные. Площадь после реального монтажа уточняется; одинаковая геометрия B/C здесь нужна только для сравнения.
A31: Проходы: расчёт по наружному корпусу кровати
A32: Наружная ширина корпуса кровати | B32: 1.8 | C32: м | D32: Условный корпус для матраса1600×2000мм; уточнить выбранную модель мебели.
A33: Наружная длина корпуса кровати | B33: 2.15 | C33: м | D33: Условный корпус для матраса1600×2000мм; уточнить выбранную модель мебели.
A35: Боковой проход при центре кровати | B35: =('Исходные'!B28-B32)/2 -> 0.6 | C35: м | D35: До штор, радиатора, ручек и местных выступов; размер не является монтажным заданием.
A36: Проход у ног | B36: ='Исходные'!B21-B33 -> 0.95 | C36: м | D36: До штор, радиатора, ручек и местных выступов; размер не является монтажным заданием.
A37: Условное открытие кухня–гостиная | B37: ='Исходные'!B20-'Исходные'!B22-'Исходные'!B28-'Исходные'!B29 -> 1.33 | C37: м | D37: До штор, радиатора, ручек и местных выступов; размер не является монтажным заданием.
A39: Ширина600мм по бокам относится к проходу вдоль корпуса. Прикроватные полки могут локально занять часть пространства у изголовья. Проверить фактическую мебель, окно и штору.

Sheet Бюджет
A1: План распределения 7 млн ₸
A2: НЕ рыночная смета. Лимиты для запроса предложений; крупная техника исключена.
A3: СИНИЕ ЯЧЕЙКИ — можно менять · тёмные числа — формулы · размеры и стоимости требуют проверки
A4: Статья | B4: Лимит | C4: Доля бюджета | D4: Комплектность и принцип распределения
A5: Обмеры, проект, доставка и организация | B5: 250000 | C5: =B5/'Исходные'!$B$9 -> 0.035714286 | D5: Включить все сопутствующие расходы. Комплектность проекта уточняется.
A6: Подготовка и отделка пола, стен, потолков | B6: 1500000 | C6: =B6/'Исходные'!$B$9 -> 0.21428571 | D6: Материалы, расходники и работа; без изменения несущих конструкций.
A7: Санузел, сантехника и разводка | B7: 900000 | C7: =B7/'Исходные'!$B$9 -> 0.12857143 | D7: Оборудование, материалы и работа; действительная цена — после обмера и предложений.
A8: Электрика и освещение | B8: 600000 | C8: =B8/'Исходные'!$B$9 -> 0.085714286 | D8: Материалы, светильники и монтаж; проверить выделенную мощность.
A9: Двери 2600 мм и перегородки / стекло | B9: 650000 | C9: =B9/'Исходные'!$B$9 -> 0.092857143 | D9: Общий лимит. Не подтверждает рыночную стоимость высоких дверей или системы C.
A10: Кухонная мебель и столешница | B10: 1050000 | C10: =B10/'Исходные'!$B$9 -> 0.15 | D10: Без крупной техники. Состав и фурнитура — после коммерческого предложения.
A11: Основная мебель и хранение | B11: 850000 | C11: =B11/'Исходные'!$B$9 -> 0.12142857 | D11: Кровать, диван / кресло, стол, шкафы; итоговый состав зависит от планировки.
A12: Текстиль и небольшой декор | B12: 200000 | C12: =B12/'Исходные'!$B$9 -> 0.028571429 | D12: Шторы, в том числе для варианта C, и необходимые предметы.
A13: Вентиляция / подготовка кондиционирования | B13: 300000 | C13: =B13/'Исходные'!$B$9 -> 0.042857143 | D13: Состав оборудования и монтажа не подтверждён; не обещает готовую систему за этот лимит.
A14: Неприкосновенный резерв — минимум 10% | B14: ='Исходные'!B9*'Исходные'!B38 -> 700000 | C14: =B14/'Исходные'!B9 -> 0.1 | D14: Не тратить заранее на желаемые улучшения. Доля задаётся в исходных данных.
A15: Всего распределено | B15: =SUM(B5:B14) -> 7000000 | C15: ₸ | D15: Формула пересчитывается при изменении исходных данных.
A16: Общий лимит пользователя | B16: ='Исходные'!B9 -> 7000000 | C16: ₸ | D16: Формула пересчитывается при изменении исходных данных.
A17: Остаток бюджета (= лимит − распределено) | B17: =B16-B15 -> 0 | C17: ₸ | D17: Отрицательный остаток означает превышение бюджета.
A18: Доля резерва от бюджета | B18: =B14/B16 -> 0.1 | C18: доля | D18: Минимальная цель — 10%.
A19: Расходы без резерва | B19: =SUM(B5:B13) -> 6300000 | C19: ₸ | D19: Формула пересчитывается при изменении исходных данных.
A21: Сначала получить предложения по инженерии, санузлу, кухне и высоким дверям. Перераспределять статьи можно, но итог не должен превышать 7 млн ₸, а резерв — уменьшаться ниже 700 тыс. ₸ при текущем бюджете.
A23: A: экономию на перегородке оставить резервом или направить на хранение после договоров по обязательным работам. B/C: стоимость перегородки и дверей должна войти в лимиты; её фактическая достаточность пока не подтверждена.
A25: Все цены здесь — выбранные плановые суммы, а не прайс подрядчика. Проверить, что предложения включают материалы, расходники, работу, доставку, подъём, вывоз и необходимые налоги. Не суммировать эту таблицу с условными инвестициями листа «Сценарии».

Sheet Двери
A1: Двери с полотном 2600 мм
A2: Базовый расчёт: 3000 − 60 − 80 = 2860 мм чистой высоты. Проём 2640 мм — исключительно условный.
A3: СИНИЕ ЯЧЕЙКИ — можно менять · тёмные числа — формулы · размеры и стоимости требуют проверки
A4: Параметр | B4: Значение, мм | C4: Статус | D4: Примечание
A5: Исходная высота | B5: ='Исходные'!B30 -> 3000 | C5: исходное | D5: Подтвердить поверхности, между которыми измерена высота.
A6: Подъём пола | B6: ='Исходные'!B31 -> 60 | C6: допущение | D6: От несущей плиты до чистого пола.
A7: Опуск потолка | B7: ='Исходные'!B32 -> 80 | C7: допущение | D7: От низа перекрытия до чистого потолка.
A8: Расчётная чистая высота | B8: =B5-B6-B7 -> 2860 | C8: расчёт | D8: Не является подтверждённым натурным размером.
A9: Высота дверного полотна | B9: ='Исходные'!B33 -> 2600 | C9: пожелание | D9: Санузел и спальня B/C; между кухней и гостиной дверь не требуется.
A10: Условная высота строительного проёма | B10: ='Исходные'!B34 -> 2640 | C10: НЕ монтажный размер | D10: Точный проём — по монтажной карте выбранной системы.
A11: Над полотном до чистого потолка | B11: =B8-B9 -> 260 | C11: геометрия | D11: Не подтверждает наличие места для перемычки и потолочного узла.
A12: Над условным проёмом до потолка | B12: =B8-B10 -> 220 | C12: геометрия | D12: Не подтверждает возможность изменения существующего проёма.
A13: Верх условного проёма от плиты пола | B13: =B10+B6 -> 2700 | C13: расчёт | D13: Только при подтверждённой базе отметок и пироге пола.
A16: Проверка нескольких вариантов пола и потолка
A17: Сценарий | B17: Пол, мм | C17: Потолок, мм | D17: Чистая высота | E17: Над полотном | F17: Над усл. проёмом
A18: Минимальные трассы | B18: 60 | C18: 50 | D18: ='Исходные'!$B$30-B18-C18 -> 2890 | E18: =D18-'Исходные'!$B$33 -> 290 | F18: =D18-'Исходные'!$B$34 -> 250
A19: Базовая модель | B19: ='Исходные'!B31 -> 60 | C19: ='Исходные'!B32 -> 80 | D19: ='Исходные'!$B$30-B19-C19 -> 2860 | E19: =D19-'Исходные'!$B$33 -> 260 | F19: =D19-'Исходные'!$B$34 -> 220
A20: Значительное опускание | B20: 120 | C20: 150 | D20: ='Исходные'!$B$30-B20-C20 -> 2730 | E20: =D20-'Исходные'!$B$33 -> 130 | F20: =D20-'Исходные'!$B$34 -> 90
A21: Альтернативный узел | B21: 90 | C21: 90 | D21: ='Исходные'!$B$30-B21-C21 -> 2820 | E21: =D21-'Исходные'!$B$33 -> 220 | F21: =D21-'Исходные'!$B$34 -> 180
A23: Если 3000 мм уже измерены между чистыми поверхностями, существующие слои повторно не вычитать. Обмерить высоты и перемычки в каждом проёме до заказа дверей.
A25: Нельзя резать железобетон или поднимать перемычку по этой таблице. Нужны подтверждение типа стен, инженерный узел и монтажная карта производителя. Усиление, крепления и петли зависят от массы и конструкции двери.
A27: В A необходимость полотен в существующих проёмах кухни/комнаты определять по допустимости открытого решения. В B/C — двери в санузел и спальню. Для C стекло и фурнитура подбираются в составе безопасной системы; штора не обеспечивает звукоизоляцию.

Sheet Сценарии
A1: Цена личного удобства
A2: Для одного жильца главный критерий — удобство. Сценарии ниже условные и не являются обещанием доходности.
A3: СИНИЕ ЯЧЕЙКИ — можно менять · тёмные числа — формулы · размеры и стоимости требуют проверки
A5: Условная доплата | B5: Вложение, ₸ | C5: Горизонт, лет | D5: Горизонт, мес | E5: Стоимость / мес | F5: Назначение
A6: Небольшая доплата | B6: 400000 | C6: ='Исходные'!B11 -> 5 | D6: =C6*12 -> 60 | E6: =B6/D6 -> 6666.6667 | F6: Распределение затрат на срок проживания; не доход и не окупаемость.
A7: Средняя доплата | B7: 800000 | C7: ='Исходные'!B11 -> 5 | D7: =C7*12 -> 60 | E7: =B7/D7 -> 13333.333 | F7: Распределение затрат на срок проживания; не доход и не окупаемость.
A8: Большая доплата | B8: 1200000 | C8: ='Исходные'!B11 -> 5 | D8: =C8*12 -> 60 | E8: =B8/D8 -> 20000 | F8: Распределение затрат на срок проживания; не доход и не окупаемость.
A10: При горизонте 5 лет доплаты 0,4 / 0,8 / 1,2 млн ₸ соответствуют примерно 6,7 / 13,3 / 20 тыс. ₸ в месяц. Это не цены вариантов A/B/C и не дополнительная сумма поверх утверждённого бюджета: реальную разницу нужно определить сметами.
A12: Личная польза: U = 0,25×свет + 0,25×простор + 0,15×хранение + 0,15×рабочее место + 0,10×приватность + 0,05×гибкость + 0,05×соответствие бюджету. Оценки 1–5 выставляются после проверки планов; веса предложены для одного жильца.
A14: A — отправная точка без перепланировки; C — компромисс света и возможности закрыть кровать шторой; B — при выраженной потребности в закрытой спальне. Допустимость, безопасность и бюджет — обязательные условия, баллами их компенсировать нельзя.
A17: Вторично: условная аренда, если назначение квартиры когда-нибудь изменится
A18: ИСКУССТВЕННЫЕ СЦЕНАРИИ. Ставки аренды и цены сделок в Астане не исследованы. Предполагается одинаковая заполняемость сравниваемых квартир. Кредит, дисконтирование и дополнительные налоги не учтены.
A20: Сценарий | B20: Доп. вложение | C20: Δ ставки / мес | D20: Заполняемость | E20: Δ поток / мес | F20: Δ поток / год | G20: Простая окуп., лет
A21: Низкая условная премия | B21: ='Исходные'!$B$37 -> 1200000 | C21: 10000 | D21: ='Исходные'!$B$35 -> 0.92 | E21: =C21*D21-'Исходные'!$B$36 -> 6200 | F21: =E21*12 -> 74400 | G21: =IF(F21>0,B21/F21,"Нет окупаемости") -> 16.129032
A22: Средняя условная премия | B22: ='Исходные'!$B$37 -> 1200000 | C22: 25000 | D22: ='Исходные'!$B$35 -> 0.92 | E22: =C22*D22-'Исходные'!$B$36 -> 20000 | F22: =E22*12 -> 240000 | G22: =IF(F22>0,B22/F22,"Нет окупаемости") -> 5
A23: Высокая условная премия | B23: ='Исходные'!$B$37 -> 1200000 | C23: 40000 | D23: ='Исходные'!$B$35 -> 0.92 | E23: =C23*D23-'Исходные'!$B$36 -> 33800 | F23: =E23*12 -> 405600 | G23: =IF(F23>0,B23/F23,"Нет окупаемости") -> 2.9585799
A25: Требуемая премия ставки для заданного горизонта | B25: =('Исходные'!B37/(12*'Исходные'!B11)+'Исходные'!B36)/'Исходные'!B35 -> 25000 | C25: При текущих условных данных: +25 000 ₸/мес для простого возврата вложения за 5 лет. Это математический порог, не прогноз рыночной надбавки.
A27: Формула аренды при одинаковой заполняемости: ΔCFгод = 12 × (ΔR × O − ΔCмес). При разных O сравнивать 12 × [(Rевро × Oевро − R1к × O1к) − ΔCмес]. Простая окупаемость применима только при положительном дополнительном потоке.
A29: Для перепродажи: дополнительная прибыль = премия цены продажи − дополнительные вложения − дополнительные расходы, налоги и стоимость времени. Отдельную премию за двери 2600 мм без рыночных данных обещать нельзя.
